x12_edi_tools/__init__.py
x12_edi_tools/batch_processor.py
x12_edi_tools/dental_claim_processor.py
x12_edi_tools/dental_code_validator.py
x12_edi_tools/eligibility_checker.py
x12_edi_tools/remittance_advise_parser.py
x12_edi_tools/x12_generator.py
x12_edi_tools/x12_parser.py
x12_edi_tools/x_12_api_wrapper.py
x12_edi_tools/x_12_converter.py
x12_edi_tools/x_12_database_integrator.py
x12_edi_tools/x_12_encryptor.py
x12_edi_tools/x_12_logger.py
x12_edi_tools/x_12_validator.py
x12_edi_tools/x_12_visualizer.py
x12_edi_tools-0.1.2.dist-info/METADATA
x12_edi_tools-0.1.2.dist-info/WHEEL
x12_edi_tools-0.1.2.dist-info/top_level.txt
x12_edi_tools-0.1.2.dist-info/RECORD
