Metadata-Version: 2.1
Name: x12-edi-tools
Version: 0.1.2
Summary: A comprehensive set of tools for working with X12 EDI files
Home-page: https://github.com/copyleftdev/x12-edi-tools
Author: Don Johnson
Author-email: dj@codetestcode.io
Classifier: Development Status :: 3 - Alpha
Classifier: Intended Audience :: Developers
Classifier: License :: OSI Approved :: MIT License
Classifier: Operating System :: OS Independent
Classifier: Programming Language :: Python :: 3
Classifier: Programming Language :: Python :: 3.7
Classifier: Programming Language :: Python :: 3.8
Classifier: Programming Language :: Python :: 3.9
Requires-Python: >=3.7
Requires-Dist: requests>=2.25.1
Requires-Dist: cryptography>=3.4.7
